sap/__init__.py
sap/xssec/__init__.py
sap/xssec/constants.py
sap/xssec/jwt_audience_validator.py
sap/xssec/jwt_validation_facade.py
sap/xssec/key_cache.py
sap/xssec/key_cache_v2.py
sap/xssec/key_tools.py
sap/xssec/security_context.py
sap/xssec/security_context_ias.py
sap/xssec/security_context_xsuaa.py
sap_xssec-4.2.2.data/data/CHANGELOG.md
sap_xssec-4.2.2.data/data/version.txt
sap_xssec-4.2.2.dist-info/LICENSE
sap_xssec-4.2.2.dist-info/METADATA
sap_xssec-4.2.2.dist-info/WHEEL
sap_xssec-4.2.2.dist-info/top_level.txt
sap_xssec-4.2.2.dist-info/RECORD
